links_devops
