Metadata-Version: 1.1
Name: links-devops
Version: 0.1.7
Summary: Fabric deployment script.
Home-page: https://linkscreative.codebasehq.com/projects/links-creative/repositories/devops
Author: James Cleveland
Author-email: james@dapperdogstudios.com
License: UNKNOWN
Platform: UNKNOWN
Classifier: Environment :: Web Environment
Classifier: Intended Audience :: Developers
Classifier: License :: OSI Approved :: BSD License
Classifier: Operating System :: OS Independent
Classifier: Programming Language :: Python
Classifier: Framework :: Django
